LICENSE
README.md
setup.py
jismesh_raster/__init__.py
jismesh_raster/rasterize.py
jismesh_raster.egg-info/PKG-INFO
jismesh_raster.egg-info/SOURCES.txt
jismesh_raster.egg-info/dependency_links.txt
jismesh_raster.egg-info/entry_points.txt
jismesh_raster.egg-info/requires.txt
jismesh_raster.egg-info/top_level.txt