Metadata-Version: 2.1
Name: jismesh-raster
Version: 0.3.1
Summary: Generate raster from jismesh-based data. jismesh=Japan Standard Mesh
Home-page: https://github.com/Kanahiro/jismesh-raster
Author: Kanahiro Iguchi
License: MIT
Platform: UNKNOWN
License-File: LICENSE
